nbprg_auth/__init__.py
nbprg_auth/main.py
nbprg_auth-0.0.1.dist-info/METADATA
nbprg_auth-0.0.1.dist-info/WHEEL
nbprg_auth-0.0.1.dist-info/top_level.txt
nbprg_auth-0.0.1.dist-info/RECORD
